torch_agents/__init__.py
torch_agents/agents.py
torch_agents/environments.py
torch_agents/explore.py
torch_agents/memory.py
torch_agents/networks.py
torch_agents/schedule.py
torch_agents/sumtree.py
torch_agents/test_schedule.py
torch_agents-0.0.1.dist-info/LICENSE
torch_agents-0.0.1.dist-info/METADATA
torch_agents-0.0.1.dist-info/WHEEL
torch_agents-0.0.1.dist-info/top_level.txt
torch_agents-0.0.1.dist-info/RECORD
