Metadata-Version: 2.1
Name: torch-agents
Version: 0.0.1
Summary: Easy Deep Reinforcement Learning for PyTorch
Home-page: https://github.com/leereeves/torch_agents
Project-URL: Bug Tracker, https://github.com/leereeves/torch_agents/issues
Classifier: Programming Language :: Python :: 3
Classifier: License :: OSI Approved :: Apache Software License
Classifier: Operating System :: OS Independent
License-File: LICENSE
Requires-Dist: requests
Requires-Dist: importlib-metadata ; python_version < "3.8"
